{"Shampoo":"Loreal Professional Serie Expert","Conditioner":"Loreal Paris Rapid Reviver","Hairoil":"Mamaearth Rice Hair Oil","Hairserum":"Livion Serum","Haircolor":"Biotique Herb Hair Color","Hairmasks":"Tresemme Deep Smoothing Mask"}{"Shampoo":"Mama Earth Rice Water Shampoo","Conditioner":"Sebastian Professional Penetraitt","Hairoil":"Moroccanoil Treatment Oil","Hairserum":"Streax Professional Serum ","Haircolor":"Streax Coffee Collection","Hairmasks":"Mamaearth Argan Hair Mask"}{"Shampoo":"Tresemme Keratin Smooth","Conditioner":"Matrix Opti Care ","Hairoil":"Forest Essential Oil","Hairserum":"Matrix Opti Care Professional Serum","Haircolor":"Revlon Colorsilk Hair Color","Hairmasks":"SP Luxe Oil Keratin Restore Mask"}{"Shampoo":"Mamaearth Onion Shampoo","Conditioner":"Herbal Essences","Hairoil":"Indulekha Bringha Hair Oil","Hairserum":"LOreal Paris Total Repair 5 Serum","Haircolor":"Godrej Nupur Henna","Hairmasks":"Wella Professionals Renewing Mask "}{"Shampoo":"Wella Professionals","Conditioner":"Loreal Paris Dream Lengths","Hairoil":"Max Care Virgin Coconut Oil","Hairserum":"Tresemme Keratin Smooth Hair Serum","Haircolor":"Joves Herbal Henna","Hairmasks":"Dove Intense Damage Repair Hair Mask"}{"Shampoo":"GK Hair Balancing Shampoo","Conditioner":"Dove Intense Repair Conditioner","Hairoil":"Wella Professional Luminous Oil","Hairserum":"Matrix Biolage Serum","Haircolor":"LOreal Paris Casting Creme Gloss","Hairmasks":"Mamaearth Rice Water Hair Mask"}